temporary_number
