Metadata-Version: 2.1
Name: temporary-number
Version: 1.0.1
Summary: Simple TempSMS Scraper
Home-page: http://pypi.python.org/pypi/temporary-number
Author: @ham_86
License: MIT
Project-URL: Homepage, https://github.com/hamutan-86/Temporary-Number
License-File: LICENSE.txt
Requires-Dist: tls-client
Requires-Dist: beautifulsoup4
Requires-Dist: lxml
